[
  {"kind":"benchmark","partitioning":"worker-offload","latency":0,"scope":"resident-head","sampleRate":48000,"contextRate":96000,"quantumFrames":64,"channels":2,"irSeconds":10,"renderSeconds":3,"medianQuantumUs":15.7,"worstQuantumUs":241.5,"halfDeadlineUs":666.666667,"totalProcessMs":42.9184,"prepareMs":0.7903,"footprintBytes":4158240,"wasmHeapBytes":16777216,"allocationViolations":0,"finite":true},
  {"kind":"benchmark","partitioning":"worker-offload","latency":128,"scope":"resident-head","sampleRate":48000,"contextRate":96000,"quantumFrames":64,"channels":2,"irSeconds":10,"renderSeconds":3,"medianQuantumUs":7.15,"worstQuantumUs":280.4,"halfDeadlineUs":666.666667,"totalProcessMs":14.8429,"prepareMs":0.1102,"footprintBytes":4160288,"wasmHeapBytes":16777216,"allocationViolations":0,"finite":true},
  {"kind":"benchmark","partitioning":"worker-offload","latency":256,"scope":"resident-head","sampleRate":48000,"contextRate":96000,"quantumFrames":64,"channels":2,"irSeconds":10,"renderSeconds":3,"medianQuantumUs":1.9,"worstQuantumUs":294.7,"halfDeadlineUs":666.666667,"totalProcessMs":13.1082,"prepareMs":0.1104,"footprintBytes":4151928,"wasmHeapBytes":16777216,"allocationViolations":0,"finite":true},
  {"kind":"benchmark","partitioning":"worker-offload","latency":512,"scope":"resident-head","sampleRate":48000,"contextRate":96000,"quantumFrames":64,"channels":2,"irSeconds":10,"renderSeconds":3,"medianQuantumUs":0.8,"worstQuantumUs":205,"halfDeadlineUs":666.666667,"totalProcessMs":8.7486,"prepareMs":0.101,"footprintBytes":4135376,"wasmHeapBytes":16777216,"allocationViolations":0,"finite":true},
  {"kind":"benchmark","partitioning":"worker-offload","latency":1024,"scope":"resident-head","sampleRate":48000,"contextRate":96000,"quantumFrames":64,"channels":2,"irSeconds":10,"renderSeconds":3,"medianQuantumUs":0.5,"worstQuantumUs":53.7,"halfDeadlineUs":666.666667,"totalProcessMs":5.3882,"prepareMs":0.0919,"footprintBytes":4102440,"wasmHeapBytes":16777216,"allocationViolations":0,"finite":true}
]
