{
  "formatVersion": 1,
  "type": "RSReverbPlugin",
  "id": "default-impulse",
  "stimulus": "imp",
  "sampleRate": 48000,
  "channels": 2,
  "frameCount": 16001,
  "blockSize": 128,
  "channelMode": "stereo",
  "channel": null,
  "caseIndex": 0,
  "seed": "0xeffe7a5e",
  "params": {
    "pd": 10,
    "rs": 10,
    "rt": 2.4,
    "ds": 8,
    "df": 0.7,
    "dp": 80,
    "hd": 2000,
    "ld": 200,
    "mx": 16
  },
  "events": [],
  "tolerance": {
    "abs": 0.0001,
    "policy": "per-sample"
  },
  "jsEngineHash": "dfa7e203c232a3fbb94ef9ab206070e3ef17d9558c1bebf7b42a6b83c0e931c1",
  "outputFloats": 32002,
  "byteLength": 128008,
  "binary": "case-001.f32"
}
