{
  "formatVersion": 1,
  "type": "ToneControlPlugin",
  "id": "mid-minimum",
  "stimulus": "sweep",
  "sampleRate": 44100,
  "channels": 2,
  "frameCount": 255,
  "blockSize": 127,
  "channelMode": "stereo",
  "channel": null,
  "caseIndex": 4,
  "seed": "0xeffe7a5a",
  "params": {
    "bs": 0,
    "md": -24,
    "tr": 0
  },
  "events": [],
  "tolerance": {
    "abs": 0.00001,
    "policy": "per-sample"
  },
  "jsEngineHash": "594cab40e39d1332770bdf04b8898ad6f0f0bdb28fb9feab8e915038504ceaad",
  "outputFloats": 510,
  "byteLength": 2040,
  "binary": "case-005.f32"
}
