{
  "formatVersion": 1,
  "type": "PitchShifterPlugin",
  "id": "downward-maximum-window-mono",
  "stimulus": "sweep",
  "sampleRate": 48000,
  "channels": 1,
  "frameCount": 112001,
  "blockSize": 113,
  "channelMode": "mono",
  "channel": "L",
  "caseIndex": 1,
  "seed": "0xeffe7a5f",
  "params": {
    "ps": -6,
    "ft": -50,
    "ws": 500,
    "xf": 20
  },
  "events": [],
  "tolerance": {
    "abs": 0.00001,
    "policy": "per-sample"
  },
  "jsEngineHash": "24b5f11f1abf2a32d77a8a7b98f9b4a0111739381e676775d657211b98472805",
  "outputFloats": 112001,
  "byteLength": 448004,
  "binary": "case-002.f32"
}
